rapt2/__init__.py
rapt2/rapt.py
rapt2/transformers/__init__.py
rapt2/transformers/base_translator.py
rapt2/transformers/qtree/__init__.py
rapt2/transformers/qtree/constants.py
rapt2/transformers/qtree/operators.py
rapt2/transformers/qtree/qtree_translator.py
rapt2/transformers/qtree/test_trees.tex
rapt2/transformers/sql/__init__.py
rapt2/transformers/sql/sql_translator.py
rapt2/treebrd/__init__.py
rapt2/treebrd/attributes.py
rapt2/treebrd/condition_node.py
rapt2/treebrd/errors.py
rapt2/treebrd/grammars/__init__.py
rapt2/treebrd/grammars/condition_grammar.py
rapt2/treebrd/grammars/core_grammar.py
rapt2/treebrd/grammars/dependency_grammar.py
rapt2/treebrd/grammars/extended_grammar.py
rapt2/treebrd/grammars/proto_grammar.py
rapt2/treebrd/grammars/syntax.py
rapt2/treebrd/node.py
rapt2/treebrd/schema.py
rapt2/treebrd/treebrd.py
rapt2/treebrd/utility.py
rapt2-0.4.3.dist-info/WHEEL
rapt2-0.4.3.dist-info/entry_points.txt
rapt2-0.4.3.dist-info/METADATA
rapt2-0.4.3.dist-info/RECORD
