Metadata-Version: 2.3
Name: rapt2
Version: 0.4.3
Summary: Relational algebra parsing tools
Keywords: relational-algebra,parser,database,query
Author: Aidan Bailey
License: 
